{
	"configurations" : 
	[
		{
			"directories" : 
			[
				{
					"build" : ".",
					"jsonFile" : "directory-.-Debug-d0094a50bb2071803777.json",
					"minimumCMakeVersion" : 
					{
						"string" : "3.20"
					},
					"projectIndex" : 0,
					"source" : ".",
					"targetIndexes" : 
					[
						0
					]
				}
			],
			"name" : "Debug",
			"projects" : 
			[
				{
					"directoryIndexes" : 
					[
						0
					],
					"name" : "Richardson_method_to_solve_ALS",
					"targetIndexes" : 
					[
						0
					]
				}
			],
			"targets" : 
			[
				{
					"directoryIndex" : 0,
					"id" : "Richardson_method_to_solve_ALS::@6890427a1f51a3e7e1df",
					"jsonFile" : "target-Richardson_method_to_solve_ALS-Debug-63a0cf170f5832fd0277.json",
					"name" : "Richardson_method_to_solve_ALS",
					"projectIndex" : 0
				}
			]
		}
	],
	"kind" : "codemodel",
	"paths" : 
	{
		"build" : "D:/CLionProjects/C++/Richardson_method_to_solve_ALS/cmake-build-debug",
		"source" : "D:/CLionProjects/C++/Richardson_method_to_solve_ALS"
	},
	"version" : 
	{
		"major" : 2,
		"minor" : 3
	}
}
